Metadata-Version: 2.1
Name: cuda_float_compress
Version: 0.2.3
Summary: A PyTorch CUDA extension for floating-point compression
Home-page: https://github.com/catid/cuda_float_compress
Author: catid
Author-email: mrcatid@gmail.com
Project-URL: Bug Tracker, https://github.com/catid/cuda_float_compress/issues
Classifier: Programming Language :: Python :: 3
Classifier: License :: OSI Approved :: BSD License
Classifier: Operating System :: OS Independent
Requires-Python: >=3.7
License-File: LICENSE
Requires-Dist: torch
Requires-Dist: numpy
